LICENSE
README.md
setup.py
cloudmersive_phishing_api_client/__init__.py
cloudmersive_phishing_api_client/api_client.py
cloudmersive_phishing_api_client/configuration.py
cloudmersive_phishing_api_client/rest.py
cloudmersive_phishing_api_client.egg-info/PKG-INFO
cloudmersive_phishing_api_client.egg-info/SOURCES.txt
cloudmersive_phishing_api_client.egg-info/dependency_links.txt
cloudmersive_phishing_api_client.egg-info/requires.txt
cloudmersive_phishing_api_client.egg-info/top_level.txt
cloudmersive_phishing_api_client/api/__init__.py
cloudmersive_phishing_api_client/api/phishing_detection_api.py
cloudmersive_phishing_api_client/models/__init__.py
cloudmersive_phishing_api_client/models/advanced_email_detection_request.py
cloudmersive_phishing_api_client/models/phishing_detection_advanced_request.py
cloudmersive_phishing_api_client/models/phishing_detection_advanced_response.py
cloudmersive_phishing_api_client/models/phishing_detection_email_advanced_response.py
cloudmersive_phishing_api_client/models/phishing_detection_response.py
test/__init__.py
test/test_advanced_email_detection_request.py
test/test_phishing_detection_advanced_request.py
test/test_phishing_detection_advanced_response.py
test/test_phishing_detection_api.py
test/test_phishing_detection_email_advanced_response.py
test/test_phishing_detection_response.py